Metadata-Version: 2.4
Name: DataFlow-421
Version: 0.2.16
License-File: LICENSE
Requires-Dist: av==12.3.0
Requires-Dist: datasets==2.21.0
Requires-Dist: decord==0.6.0
Requires-Dist: jsonargparse==4.32.0
Requires-Dist: numpy==1.26.4
Requires-Dist: opencv-python==4.10.0.84
Requires-Dist: scipy==1.13.1
Requires-Dist: torch==2.4.0
Requires-Dist: tqdm==4.66.5
Requires-Dist: transformers==4.52.4
Requires-Dist: colorlog==6.9.0
Requires-Dist: vllm==0.6.3
Requires-Dist: clickhouse_driver==0.2.9
Requires-Dist: aisuite==0.1.11
Requires-Dist: docstring_parser==0.16
Requires-Dist: math_verify==0.7.0
Requires-Dist: word2number==1.1
Requires-Dist: accelerate==1.7.0
Requires-Dist: rapidfuzz==3.13.0
Requires-Dist: tree-sitter==0.21.0
Requires-Dist: tree-sitter-languages==1.10.2
Provides-Extra: image
Requires-Dist: imagededup==0.3.2; extra == "image"
Requires-Dist: fsspec==2024.6.1; extra == "image"
Requires-Dist: ftfy==6.2.3; extra == "image"
Requires-Dist: nltk==3.8; extra == "image"
Requires-Dist: openai-clip==1.0.1; extra == "image"
Requires-Dist: regex==2024.7.24; extra == "image"
Requires-Dist: safetensors==0.4.4; extra == "image"
Requires-Dist: scikit-learn==1.5.1; extra == "image"
Requires-Dist: setuptools==72.1.0; extra == "image"
Requires-Dist: timm==1.0.8; extra == "image"
Requires-Dist: torchvision==0.19.0; extra == "image"
Requires-Dist: vllm==0.6.0; extra == "image"
Provides-Extra: video
Requires-Dist: einops==0.8.0; extra == "video"
Requires-Dist: pandas==2.2.2; extra == "video"
Requires-Dist: PyYAML==6.0.2; extra == "video"
Requires-Dist: scikit-video==1.1.11; extra == "video"
Requires-Dist: timm==1.0.8; extra == "video"
Requires-Dist: torchvision==0.19.0; extra == "video"
Provides-Extra: text
Requires-Dist: fasttext==0.9.3; extra == "text"
Requires-Dist: filelock==3.15.4; extra == "text"
Requires-Dist: google-api-core==2.19.1; extra == "text"
Requires-Dist: google-api-python-client==2.140.0; extra == "text"
Requires-Dist: google-auth==2.33.0; extra == "text"
Requires-Dist: google-auth-httplib2==0.2.0; extra == "text"
Requires-Dist: googleapis-common-protos==1.63.2; extra == "text"
Requires-Dist: kenlm==0.3.0; extra == "text"
Requires-Dist: langkit==0.0.33; extra == "text"
Requires-Dist: loguru==0.7.2; extra == "text"
Requires-Dist: matplotlib==3.9.2; extra == "text"
Requires-Dist: multiprocess==0.70.16; extra == "text"
Requires-Dist: openai==1.44.1; extra == "text"
Requires-Dist: prettytable==3.11.0; extra == "text"
Requires-Dist: pyspark==3.5.2; extra == "text"
Requires-Dist: sentencepiece==0.2.0; extra == "text"
Requires-Dist: vendi-score==0.0.3; extra == "text"
Requires-Dist: wget==3.2; extra == "text"
Requires-Dist: nltk; extra == "text"
Requires-Dist: presidio_analyzer[transformers]; extra == "text"
Requires-Dist: presidio_anonymizer; extra == "text"
Requires-Dist: gdown; extra == "text"
Requires-Dist: simhash; extra == "text"
Requires-Dist: datasketch; extra == "text"
Requires-Dist: gensim; extra == "text"
Requires-Dist: pot; extra == "text"
Requires-Dist: hlepor; extra == "text"
Requires-Dist: nptyping; extra == "text"
Requires-Dist: sacrebleu; extra == "text"
Requires-Dist: bert_score; extra == "text"
Provides-Extra: all
Requires-Dist: imagededup==0.3.2; extra == "all"
Requires-Dist: fsspec==2024.6.1; extra == "all"
Requires-Dist: ftfy==6.2.3; extra == "all"
Requires-Dist: nltk==3.8; extra == "all"
Requires-Dist: openai-clip==1.0.1; extra == "all"
Requires-Dist: regex==2024.7.24; extra == "all"
Requires-Dist: safetensors==0.4.4; extra == "all"
Requires-Dist: scikit-learn==1.5.1; extra == "all"
Requires-Dist: setuptools==72.1.0; extra == "all"
Requires-Dist: timm==1.0.8; extra == "all"
Requires-Dist: torchvision==0.19.0; extra == "all"
Requires-Dist: vllm==0.6.0; extra == "all"
Requires-Dist: einops==0.8.0; extra == "all"
Requires-Dist: pandas==2.2.2; extra == "all"
Requires-Dist: PyYAML==6.0.2; extra == "all"
Requires-Dist: scikit-video==1.1.11; extra == "all"
Requires-Dist: timm==1.0.8; extra == "all"
Requires-Dist: fasttext==0.9.3; extra == "all"
Requires-Dist: filelock==3.15.4; extra == "all"
Requires-Dist: google-api-core==2.19.1; extra == "all"
Requires-Dist: google-api-python-client==2.140.0; extra == "all"
Requires-Dist: google-auth==2.33.0; extra == "all"
Requires-Dist: google-auth-httplib2==0.2.0; extra == "all"
Requires-Dist: googleapis-common-protos==1.63.2; extra == "all"
Requires-Dist: kenlm==0.3.0; extra == "all"
Requires-Dist: langkit==0.0.33; extra == "all"
Requires-Dist: loguru==0.7.2; extra == "all"
Requires-Dist: matplotlib==3.9.2; extra == "all"
Requires-Dist: multiprocess==0.70.16; extra == "all"
Requires-Dist: openai==1.44.1; extra == "all"
Requires-Dist: prettytable==3.11.0; extra == "all"
Requires-Dist: pyspark==3.5.2; extra == "all"
Requires-Dist: sentencepiece==0.2.0; extra == "all"
Requires-Dist: vendi-score==0.0.3; extra == "all"
Requires-Dist: wget==3.2; extra == "all"
Requires-Dist: presidio_analyzer[transformers]; extra == "all"
Requires-Dist: presidio_anonymizer; extra == "all"
Requires-Dist: aisuite; extra == "all"
Requires-Dist: math_verify; extra == "all"
Requires-Dist: tinydb; extra == "all"
Requires-Dist: word2number; extra == "all"
Requires-Dist: docstring_parser; extra == "all"
Requires-Dist: colorlog; extra == "all"
Requires-Dist: guesslang; extra == "all"
Dynamic: license-file
Dynamic: provides-extra
Dynamic: requires-dist
